{"cameraMode":{"drawMode":0,"name":"Shaded","section":"Shading Mode"},"sceneLighting":true,"audioPlay":false,"sceneViewState":{"m_AlwaysRefresh":false,"showFog":true,"showSkybox":true,"showFlares":true,"showImageEffects":true,"showParticleSystems":true,"showVisualEffectGraphs":true,"m_FxEnabled":true},"in2DMode":false,"pivot":{"x":-0.5542591214179993,"y":0.33637791872024538,"z":-0.2264392375946045},"rotation":{"x":-0.14325639605522157,"y":-0.5828316807746887,"z":0.10520021617412567,"w":-0.7929444313049316},"size":1.925020694732666,"orthographic":false}